intense/__init__.py
intense/gauge.py
intense/qc.py
intense/rulebase.py
intense/utils.py
intense-0.2.0.dist-info/METADATA
intense-0.2.0.dist-info/WHEEL
intense-0.2.0.dist-info/top_level.txt
intense-0.2.0.dist-info/RECORD
